{
    "code": 0,
    "msg": "",
    "url": null,
    "data": {
        "totalSize": 49,
        "totalPageCount": 5,
        "pageIndex": 2,
        "pageSize": 12,
        "list": [{
            "id": "f798623f-8d17-41d3-a443-cfce17c5418b",
            "title": null,
            "smallUrl": "http://lp-zhanghou-input.oss-cn-hangzhou.aliyuncs.com/source/f798623f-8d17-41d3-a443-cfce17c5418b_small.jpg",
            "visitUrl": "http://lp-zhanghou-input.oss-cn-hangzhou.aliyuncs.com/source/f798623f-8d17-41d3-a443-cfce17c5418b.jpg",
            "movUrl": "http://lp-zhanghou-input.oss-cn-hangzhou.aliyuncs.com/source/f798623f-8d17-41d3-a443-cfce17c5418b.mp4",
            "collectionFlag": false,
            "followFlag": false,
            "buyState": false,
            "tags": ["文字控", "考试", "三格式锁屏"],
            "authorAvatar": "http://lp-zhanghou-input.oss-cn-hangzhou.aliyuncs.com/user/add6707a-6cd6-43d7-bab3-2122e7be8dc0/1e92299b-43d8-4eaf-b812-9debf298b399.JPG",
            "authorId": "add6707a-6cd6-43d7-bab3-2122e7be8dc0",
            "authorName": "葛苗雨家长",
            "signature": null,
            "comType": 2,
            "statDataTypeKey": "58d56054-0cf3-4d28-a9b6-24aa3cec7cf1",
            "remark": "咳咳，走过路过别要错过。新出炉的壁纸来了。（咳咳，我是不是有点不正经。）祝我今天考试逢考必过。（谢谢鸭～）",
            "slideAdType": 0,
            "listAdType": false,
            "listAdTypeNew": 0,
            "width": null,
            "height": null,
            "videoTime": null,
            "visitCount": null,
            "showAdType": null,
            "privateAdImgUrl": null,
            "pay": false
        }, {
            "id": "8689d87c-33e1-4968-b7ea-36e8daa2c725",
            "title": null,
            "smallUrl": "http://lp-zhanghou-input.oss-cn-hangzhou.aliyuncs.com/source/8689d87c-33e1-4968-b7ea-36e8daa2c725_small.jpg",
            "visitUrl": "http://lp-zhanghou-input.oss-cn-hangzhou.aliyuncs.com/source/8689d87c-33e1-4968-b7ea-36e8daa2c725.jpg",
            "movUrl": "http://lp-zhanghou-input.oss-cn-hangzhou.aliyuncs.com/source/8689d87c-33e1-4968-b7ea-36e8daa2c725.mp4",
            "collectionFlag": false,
            "followFlag": false,
            "buyState": false,
            "tags": ["帅哥", "易烊千玺", "三格式锁屏"],
            "authorAvatar": "http://lp-zhanghou-input.oss-cn-hangzhou.aliyuncs.com/user/399ff78f-0bdf-4af9-bc35-3b9aacf8838c/3610ca00-2082-434e-9424-fc7b613dafa1.JPG",
            "authorId": "399ff78f-0bdf-4af9-bc35-3b9aacf8838c",
            "authorName": "颜尘距离暴富还有1%",
            "signature": null,
            "comType": 2,
            "statDataTypeKey": "58d56054-0cf3-4d28-a9b6-24aa3cec7cf1",
            "remark": "这是什么神仙颜值",
            "slideAdType": 0,
            "listAdType": false,
            "listAdTypeNew": 0,
            "width": null,
            "height": null,
            "videoTime": null,
            "visitCount": null,
            "showAdType": null,
            "privateAdImgUrl": null,
            "pay": false
        }, {
            "id": "5c0161ee-a5b7-4b70-948b-de24a59d9643",
            "title": null,
            "smallUrl": "http://lp-zhanghou-input.oss-cn-hangzhou.aliyuncs.com/source/5c0161ee-a5b7-4b70-948b-de24a59d9643_small.jpg",
            "visitUrl": "http://lp-zhanghou-input.oss-cn-hangzhou.aliyuncs.com/source/5c0161ee-a5b7-4b70-948b-de24a59d9643.jpg",
            "movUrl": "http://lp-zhanghou-input.oss-cn-hangzhou.aliyuncs.com/source/5c0161ee-a5b7-4b70-948b-de24a59d9643.mp4",
            "collectionFlag": false,
            "followFlag": false,
            "buyState": false,
            "tags": null,
            "authorAvatar": "http://lp-zhanghou-input.oss-cn-hangzhou.aliyuncs.com/user/1c7e1478-c5ca-47e8-911d-5aba88d8faff/95e55979-4898-44c2-a2c3-85c1184ce3c1.JPG",
            "authorId": "1c7e1478-c5ca-47e8-911d-5aba88d8faff",
            "authorName": "好奇心重",
            "signature": null,
            "comType": 2,
            "statDataTypeKey": "58d56054-0cf3-4d28-a9b6-24aa3cec7cf1",
            "remark": "你指尖跃动的电光,是我此生不灭的信仰",
            "slideAdType": 0,
            "listAdType": false,
            "listAdTypeNew": 0,
            "width": null,
            "height": null,
            "videoTime": null,
            "visitCount": null,
            "showAdType": null,
            "privateAdImgUrl": null,
            "pay": false
        }, {
            "id": "82c5341d-944c-4b24-9ed1-8225a57df89d",
            "title": null,
            "smallUrl": "http://lp-zhanghou-input.oss-cn-hangzhou.aliyuncs.com/source/82c5341d-944c-4b24-9ed1-8225a57df89d_small.jpg",
            "visitUrl": "http://lp-zhanghou-input.oss-cn-hangzhou.aliyuncs.com/source/82c5341d-944c-4b24-9ed1-8225a57df89d.jpg",
            "movUrl": "http://lp-zhanghou-input.oss-cn-hangzhou.aliyuncs.com/source/82c5341d-944c-4b24-9ed1-8225a57df89d.mp4",
            "collectionFlag": false,
            "followFlag": false,
            "buyState": false,
            "tags": ["三格式锁屏"],
            "authorAvatar": "http://lp-zhanghou-input.oss-cn-hangzhou.aliyuncs.com/user/b525a714-29ea-4ef8-b04b-8d2815d96d5d/48ee625b-6fd6-4fa3-a0de-4681d988ecc5.JPG",
            "authorId": "b525a714-29ea-4ef8-b04b-8d2815d96d5d",
            "authorName": "一路发",
            "signature": null,
            "comType": 2,
            "statDataTypeKey": "58d56054-0cf3-4d28-a9b6-24aa3cec7cf1",
            "remark": "美女三格动态",
            "slideAdType": 0,
            "listAdType": false,
            "listAdTypeNew": 0,
            "width": null,
            "height": null,
            "videoTime": null,
            "visitCount": null,
            "showAdType": null,
            "privateAdImgUrl": null,
            "pay": false
        }, {
            "id": "3184fd01-e6f6-4e3b-91c6-2c9253643e00",
            "title": null,
            "smallUrl": "http://lp-zhanghou-input.oss-cn-hangzhou.aliyuncs.com/source/3184fd01-e6f6-4e3b-91c6-2c9253643e00_small.jpg",
            "visitUrl": "http://lp-zhanghou-input.oss-cn-hangzhou.aliyuncs.com/source/3184fd01-e6f6-4e3b-91c6-2c9253643e00.jpg",
            "movUrl": "http://lp-zhanghou-input.oss-cn-hangzhou.aliyuncs.com/source/3184fd01-e6f6-4e3b-91c6-2c9253643e00.mp4",
            "collectionFlag": false,
            "followFlag": false,
            "buyState": false,
            "tags": ["情感语录", "三格式锁屏", "黑白文字"],
            "authorAvatar": "http://lp-zhanghou-input.oss-cn-hangzhou.aliyuncs.com/user/6b80f9ce-4f3c-4a61-9589-e5428dca1980/3d436378-216f-4291-8203-28978e891b1b.JPG",
            "authorId": "6b80f9ce-4f3c-4a61-9589-e5428dca1980",
            "authorName": "小黑",
            "signature": null,
            "comType": 2,
            "statDataTypeKey": "58d56054-0cf3-4d28-a9b6-24aa3cec7cf1",
            "remark": "动态唯美壁纸",
            "slideAdType": 0,
            "listAdType": false,
            "listAdTypeNew": 0,
            "width": null,
            "height": null,
            "videoTime": null,
            "visitCount": null,
            "showAdType": null,
            "privateAdImgUrl": null,
            "pay": false
        }, {
            "id": "0b00b008-9e55-4a97-83d0-63641ee4d450",
            "title": null,
            "smallUrl": "http://lp-zhanghou-input.oss-cn-hangzhou.aliyuncs.com/source/0b00b008-9e55-4a97-83d0-63641ee4d450_small.jpg",
            "visitUrl": "http://lp-zhanghou-input.oss-cn-hangzhou.aliyuncs.com/source/0b00b008-9e55-4a97-83d0-63641ee4d450.jpg",
            "movUrl": "http://lp-zhanghou-input.oss-cn-hangzhou.aliyuncs.com/source/0b00b008-9e55-4a97-83d0-63641ee4d450.mp4",
            "collectionFlag": false,
            "followFlag": false,
            "buyState": false,
            "tags": ["日本动漫", "终结的炽天使", "三格式锁屏"],
            "authorAvatar": "http://lp-zhanghou-input.oss-cn-hangzhou.aliyuncs.com/user/f856f1ed-8fd0-4602-aa57-f5dcd3b1491e/a982b90f-ae3d-4ee8-8031-b0bca8da64dc.JPG",
            "authorId": "f856f1ed-8fd0-4602-aa57-f5dcd3b1491e",
            "authorName": "嫰",
            "signature": null,
            "comType": 2,
            "statDataTypeKey": "58d56054-0cf3-4d28-a9b6-24aa3cec7cf1",
            "remark": "终结的炽天使",
            "slideAdType": 0,
            "listAdType": false,
            "listAdTypeNew": 0,
            "width": null,
            "height": null,
            "videoTime": null,
            "visitCount": null,
            "showAdType": null,
            "privateAdImgUrl": null,
            "pay": false
        }, {
            "id": "6dca9a4c-50d3-4662-a648-1a596dd20893",
            "title": null,
            "smallUrl": "http://lp-zhanghou-input.oss-cn-hangzhou.aliyuncs.com/source/6dca9a4c-50d3-4662-a648-1a596dd20893_small.jpg",
            "visitUrl": "http://lp-zhanghou-input.oss-cn-hangzhou.aliyuncs.com/source/6dca9a4c-50d3-4662-a648-1a596dd20893.jpg",
            "movUrl": "http://lp-zhanghou-input.oss-cn-hangzhou.aliyuncs.com/source/6dca9a4c-50d3-4662-a648-1a596dd20893.mp4",
            "collectionFlag": false,
            "followFlag": false,
            "buyState": false,
            "tags": null,
            "authorAvatar": "http://lp-zhanghou-input.oss-cn-hangzhou.aliyuncs.com/user/d384cc6f-2901-4a31-ae28-a115ddf70783/72c140da-acfd-4c87-a358-ad670a97056d.JPG",
            "authorId": "d384cc6f-2901-4a31-ae28-a115ddf70783",
            "authorName": "wlyou",
            "signature": null,
            "comType": 2,
            "statDataTypeKey": "58d56054-0cf3-4d28-a9b6-24aa3cec7cf1",
            "remark": "超喜欢这种性格反转的感觉 （黑化系列第9）",
            "slideAdType": 0,
            "listAdType": false,
            "listAdTypeNew": 0,
            "width": null,
            "height": null,
            "videoTime": null,
            "visitCount": null,
            "showAdType": null,
            "privateAdImgUrl": null,
            "pay": false
        }, {
            "id": "b3cb3ed9-55c1-4059-8474-e1f2db59a797",
            "title": null,
            "smallUrl": "http://lp-zhanghou-input.oss-cn-hangzhou.aliyuncs.com/source/b3cb3ed9-55c1-4059-8474-e1f2db59a797_small.jpg",
            "visitUrl": "http://lp-zhanghou-input.oss-cn-hangzhou.aliyuncs.com/source/b3cb3ed9-55c1-4059-8474-e1f2db59a797.jpg",
            "movUrl": "http://lp-zhanghou-input.oss-cn-hangzhou.aliyuncs.com/source/b3cb3ed9-55c1-4059-8474-e1f2db59a797.mp4",
            "collectionFlag": false,
            "followFlag": false,
            "buyState": false,
            "tags": ["张国荣", "哥哥", "三格式锁屏", "港星"],
            "authorAvatar": "http://lp-zhanghou-input.oss-cn-hangzhou.aliyuncs.com/user/41e767d3-2526-465f-9134-35c397ee0833/2498271f-711b-41fa-b17c-7a9108aca733.JPG",
            "authorId": "41e767d3-2526-465f-9134-35c397ee0833",
            "authorName": "愤怒的小鸟，我是愤怒的小鸟",
            "signature": null,
            "comType": 2,
            "statDataTypeKey": "58d56054-0cf3-4d28-a9b6-24aa3cec7cf1",
            "remark": "香港一代男星。永远喜欢哥哥。",
            "slideAdType": 0,
            "listAdType": false,
            "listAdTypeNew": 0,
            "width": null,
            "height": null,
            "videoTime": null,
            "visitCount": null,
            "showAdType": null,
            "privateAdImgUrl": null,
            "pay": false
        }, {
            "id": "5f39655e-0784-40d1-a9fb-ea55463e38f9",
            "title": null,
            "smallUrl": "http://lp-zhanghou-input.oss-cn-hangzhou.aliyuncs.com/source/5f39655e-0784-40d1-a9fb-ea55463e38f9_small.jpg",
            "visitUrl": "http://lp-zhanghou-input.oss-cn-hangzhou.aliyuncs.com/source/5f39655e-0784-40d1-a9fb-ea55463e38f9.jpg",
            "movUrl": "http://lp-zhanghou-input.oss-cn-hangzhou.aliyuncs.com/source/5f39655e-0784-40d1-a9fb-ea55463e38f9.mp4",
            "collectionFlag": false,
            "followFlag": false,
            "buyState": false,
            "tags": ["三格式锁屏", "唯美古风", "国产古风原画"],
            "authorAvatar": "http://lp-zhanghou-input.oss-cn-hangzhou.aliyuncs.com/user/48f0a08b-c665-44bc-bc04-c0c07ad9422a/c25e21a5-90f2-4262-b29d-3b6194246735.JPG",
            "authorId": "48f0a08b-c665-44bc-bc04-c0c07ad9422a",
            "authorName": "为谁画相思╮",
            "signature": null,
            "comType": 2,
            "statDataTypeKey": "58d56054-0cf3-4d28-a9b6-24aa3cec7cf1",
            "remark": "晚安啦。各位",
            "slideAdType": 0,
            "listAdType": false,
            "listAdTypeNew": 0,
            "width": null,
            "height": null,
            "videoTime": null,
            "visitCount": null,
            "showAdType": null,
            "privateAdImgUrl": null,
            "pay": false
        }, {
            "id": "977f5ecf-ffc4-4fdc-a70e-5e7e29a7346b",
            "title": null,
            "smallUrl": "http://lp-zhanghou-input.oss-cn-hangzhou.aliyuncs.com/source/977f5ecf-ffc4-4fdc-a70e-5e7e29a7346b_small.jpg",
            "visitUrl": "http://lp-zhanghou-input.oss-cn-hangzhou.aliyuncs.com/source/977f5ecf-ffc4-4fdc-a70e-5e7e29a7346b.jpg",
            "movUrl": "http://lp-zhanghou-input.oss-cn-hangzhou.aliyuncs.com/source/977f5ecf-ffc4-4fdc-a70e-5e7e29a7346b.mp4",
            "collectionFlag": false,
            "followFlag": false,
            "buyState": false,
            "tags": null,
            "authorAvatar": "http://lp-zhanghou-input.oss-cn-hangzhou.aliyuncs.com/user/ab8fda17-d490-406c-9ae9-c253179f5a51/c7efdaf7-8af0-496b-beab-1ad1de89e5fb.JPG",
            "authorId": "ab8fda17-d490-406c-9ae9-c253179f5a51",
            "authorName": "*末情*",
            "signature": null,
            "comType": 2,
            "statDataTypeKey": "58d56054-0cf3-4d28-a9b6-24aa3cec7cf1",
            "remark": "蠢萌=可爱",
            "slideAdType": 0,
            "listAdType": false,
            "listAdTypeNew": 0,
            "width": null,
            "height": null,
            "videoTime": null,
            "visitCount": null,
            "showAdType": null,
            "privateAdImgUrl": null,
            "pay": false
        }, {
            "id": "90245f83-71f7-4704-856f-b52ea84f96ca",
            "title": null,
            "smallUrl": "http://lp-zhanghou-input.oss-cn-hangzhou.aliyuncs.com/source/90245f83-71f7-4704-856f-b52ea84f96ca_small.jpg",
            "visitUrl": "http://lp-zhanghou-input.oss-cn-hangzhou.aliyuncs.com/source/90245f83-71f7-4704-856f-b52ea84f96ca.jpg",
            "movUrl": "http://lp-zhanghou-input.oss-cn-hangzhou.aliyuncs.com/source/90245f83-71f7-4704-856f-b52ea84f96ca.mp4",
            "collectionFlag": false,
            "followFlag": false,
            "buyState": false,
            "tags": ["龙女仆康娜"],
            "authorAvatar": "http://lp-zhanghou-input.oss-cn-hangzhou.aliyuncs.com/user/b9e39e8e-581e-4c0d-a1a0-775b39d2fbbf/475f71f4-3c05-4d54-a016-085c76149819.JPG",
            "authorId": "b9e39e8e-581e-4c0d-a1a0-775b39d2fbbf",
            "authorName": "速度的心跳见证你的美妙",
            "signature": null,
            "comType": 2,
            "statDataTypeKey": "58d56054-0cf3-4d28-a9b6-24aa3cec7cf1",
            "remark": "康娜领养计划！品种（饿龙），杂食动物，啥都吃，不挑食！ #萌 #可爱",
            "slideAdType": 0,
            "listAdType": false,
            "listAdTypeNew": 0,
            "width": null,
            "height": null,
            "videoTime": null,
            "visitCount": null,
            "showAdType": null,
            "privateAdImgUrl": null,
            "pay": false
        }, {
            "id": "fb107287-ba91-44d4-bc4d-a20aa5609d6f",
            "title": null,
            "smallUrl": "http://lp-zhanghou-input.oss-cn-hangzhou.aliyuncs.com/source/fb107287-ba91-44d4-bc4d-a20aa5609d6f_small.jpg",
            "visitUrl": "http://lp-zhanghou-input.oss-cn-hangzhou.aliyuncs.com/source/fb107287-ba91-44d4-bc4d-a20aa5609d6f.jpg",
            "movUrl": "http://lp-zhanghou-input.oss-cn-hangzhou.aliyuncs.com/source/fb107287-ba91-44d4-bc4d-a20aa5609d6f.mp4",
            "collectionFlag": false,
            "followFlag": false,
            "buyState": false,
            "tags": ["美女明星", "迪丽热巴", "三格式锁屏"],
            "authorAvatar": "http://lp-zhanghou-input.oss-cn-hangzhou.aliyuncs.com/user/d21c3697-56e2-4138-bee8-074609b58708/8e6d5b47-f366-45a4-8b5f-72ee11ce9f39.JPG",
            "authorId": "d21c3697-56e2-4138-bee8-074609b58708",
            "authorName": "?永远不相信?",
            "signature": null,
            "comType": 2,
            "statDataTypeKey": "58d56054-0cf3-4d28-a9b6-24aa3cec7cf1",
            "remark": "热巴小姐姐也太好看了吧！！！最后一张美到爆！手机壁纸好看到起飞٩( 'ω' )و",
            "slideAdType": 0,
            "listAdType": false,
            "listAdTypeNew": 0,
            "width": null,
            "height": null,
            "videoTime": null,
            "visitCount": null,
            "showAdType": null,
            "privateAdImgUrl": null,
            "pay": false
        }]
    }
}
