{
    "code": 0,
    "msg": "",
    "url": null,
    "data": {
        "totalSize": 21,
        "totalPageCount": 2,
        "pageIndex": 1,
        "pageSize": 12,
        "list": [{
            "id": "146cf653-4495-4a56-8bdc-66975067f0df",
            "title": null,
            "smallUrl": "http://lp-zhanghou-input.oss-cn-hangzhou.aliyuncs.com/source/146cf653-4495-4a56-8bdc-66975067f0df_small.jpg",
            "visitUrl": "http://lp-zhanghou-input.oss-cn-hangzhou.aliyuncs.com/source/146cf653-4495-4a56-8bdc-66975067f0df.jpg",
            "movUrl": "http://lp-zhanghou-input.oss-cn-hangzhou.aliyuncs.com/source/146cf653-4495-4a56-8bdc-66975067f0df.mp4",
            "collectionFlag": false,
            "followFlag": false,
            "buyState": false,
            "tags": ["安琪baby"],
            "authorAvatar": "http://lp-zhanghou-input.oss-cn-hangzhou.aliyuncs.com/user/6b5e24c5-9635-4be7-95af-0451ab5109f6/9512bd42-3638-4452-986a-1cdeece3c33c.JPG",
            "authorId": "18927e64-ef53-4fbb-a050-e0baf4fb3511",
            "authorName": "陆仁贾",
            "signature": "爱游戏聊游戏就关注陆仁贾，本人仅在抖音更新，欢迎评论区踊跃发言",
            "comType": 2,
            "statDataTypeKey": "c6f1b5a7-bd74-4214-bbd0-4a561d619411",
            "remark": "做你想做的 错了别赖我",
            "slideAdType": 0,
            "listAdType": false,
            "listAdTypeNew": 0,
            "width": null,
            "height": null,
            "videoTime": null,
            "visitCount": null,
            "showAdType": null,
            "privateAdImgUrl": null,
            "pay": false
        }, {
            "id": "ac8731e9-2215-4e0b-bbdc-051799a090bd",
            "title": null,
            "smallUrl": "http://lp-zhanghou-input.oss-cn-hangzhou.aliyuncs.com/source/ac8731e9-2215-4e0b-bbdc-051799a090bd_small.jpg",
            "visitUrl": "http://lp-zhanghou-input.oss-cn-hangzhou.aliyuncs.com/source/ac8731e9-2215-4e0b-bbdc-051799a090bd.jpg",
            "movUrl": "http://lp-zhanghou-input.oss-cn-hangzhou.aliyuncs.com/source/ac8731e9-2215-4e0b-bbdc-051799a090bd.mp4",
            "collectionFlag": false,
            "followFlag": false,
            "buyState": false,
            "tags": ["安琪baby"],
            "authorAvatar": "http://thirdqq.qlogo.cn/g?b=oidb&k=ZCnYFky5c4l66PEf6iaRGSQ&s=100&t=1592311188",
            "authorId": "9a5e641c-ce4b-465c-8e9b-86c0d734b1a5",
            "authorName": "꧁梦༒空꧂",
            "signature": null,
            "comType": 2,
            "statDataTypeKey": "c6f1b5a7-bd74-4214-bbd0-4a561d619411",
            "remark": "#一起眨眼笑  喜欢不是一件浪漫的事 喜欢你才是.",
            "slideAdType": 0,
            "listAdType": false,
            "listAdTypeNew": 0,
            "width": null,
            "height": null,
            "videoTime": null,
            "visitCount": null,
            "showAdType": null,
            "privateAdImgUrl": null,
            "pay": false
        }, {
            "id": "88d9e75e-97c9-4f99-8a66-cc9e958d3257",
            "title": null,
            "smallUrl": "http://lp-zhanghou-input.oss-cn-hangzhou.aliyuncs.com/source/88d9e75e-97c9-4f99-8a66-cc9e958d3257_small.jpg",
            "visitUrl": "http://lp-zhanghou-input.oss-cn-hangzhou.aliyuncs.com/source/88d9e75e-97c9-4f99-8a66-cc9e958d3257.jpg",
            "movUrl": "http://lp-zhanghou-input.oss-cn-hangzhou.aliyuncs.com/source/88d9e75e-97c9-4f99-8a66-cc9e958d3257.mp4",
            "collectionFlag": false,
            "followFlag": false,
            "buyState": false,
            "tags": ["安琪baby"],
            "authorAvatar": "http://thirdwx.qlogo.cn/mmopen/vi_32/bZgfCyIwrNBiaqRYgibc1ic5BBm3PylWZ9QcuaCN2HiaGGibiaAyLgKhvxqLB6dF2oG4jT2zZzeicmLUu2efKwHobF14A/132",
            "authorId": "9f24fc57-1f6c-4dbb-b796-4514d803ed88",
            "authorName": "冷",
            "signature": null,
            "comType": 2,
            "statDataTypeKey": "c6f1b5a7-bd74-4214-bbd0-4a561d619411",
            "remark": "我才二十岁 爱情可以迟到 但是 外卖不行",
            "slideAdType": 0,
            "listAdType": false,
            "listAdTypeNew": 0,
            "width": null,
            "height": null,
            "videoTime": null,
            "visitCount": null,
            "showAdType": null,
            "privateAdImgUrl": null,
            "pay": false
        }, {
            "id": "fbf1ad95-b315-41b7-8d34-0d29cbe2167f",
            "title": null,
            "smallUrl": "http://lp-zhanghou-input.oss-cn-hangzhou.aliyuncs.com/source/fbf1ad95-b315-41b7-8d34-0d29cbe2167f_small.jpg",
            "visitUrl": "http://lp-zhanghou-input.oss-cn-hangzhou.aliyuncs.com/source/fbf1ad95-b315-41b7-8d34-0d29cbe2167f.jpg",
            "movUrl": "http://lp-zhanghou-input.oss-cn-hangzhou.aliyuncs.com/source/fbf1ad95-b315-41b7-8d34-0d29cbe2167f.mp4",
            "collectionFlag": false,
            "followFlag": false,
            "buyState": false,
            "tags": ["安琪baby"],
            "authorAvatar": "http://lp-zhanghou-input.oss-cn-hangzhou.aliyuncs.com/user/eefd7aae-23ca-469f-a52e-a35909ea6091/4a80f741-02f4-4908-ad5d-b73580704540.JPG",
            "authorId": "eefd7aae-23ca-469f-a52e-a35909ea6091",
            "authorName": "小波比",
            "signature": "原创情侣动态壁纸，抖音独家首发\n喜欢请关注，持续更新哟",
            "comType": 2,
            "statDataTypeKey": "c6f1b5a7-bd74-4214-bbd0-4a561d619411",
            "remark": "握不住的手，还是趁早放开吧，那也太胖了...哈哈哈 #把回忆拼好给你 #倾心变装",
            "slideAdType": 0,
            "listAdType": false,
            "listAdTypeNew": 0,
            "width": null,
            "height": null,
            "videoTime": null,
            "visitCount": null,
            "showAdType": null,
            "privateAdImgUrl": null,
            "pay": false
        }, {
            "id": "889f096a-3035-40f5-bf4b-4a27f38fce57",
            "title": null,
            "smallUrl": "http://lp-zhanghou-input.oss-cn-hangzhou.aliyuncs.com/source/889f096a-3035-40f5-bf4b-4a27f38fce57_small.jpg",
            "visitUrl": "http://lp-zhanghou-input.oss-cn-hangzhou.aliyuncs.com/source/889f096a-3035-40f5-bf4b-4a27f38fce57.jpg",
            "movUrl": "http://lp-zhanghou-input.oss-cn-hangzhou.aliyuncs.com/source/889f096a-3035-40f5-bf4b-4a27f38fce57.mp4",
            "collectionFlag": false,
            "followFlag": false,
            "buyState": false,
            "tags": ["安琪baby"],
            "authorAvatar": "http://thirdwx.qlogo.cn/mmopen/vi_32/tUibqsmib5hOrxO17Akd8uhVK3iaDkPibXicZIHOP6nzuyv3jym1ROMJf8f7BFkprvKlh75yHgaibZFGmicgdeKrNlCmA/132",
            "authorId": "4b98c64d-c94a-40af-ada4-c65c5b65739d",
            "authorName": "元尊",
            "signature": null,
            "comType": 2,
            "statDataTypeKey": "c6f1b5a7-bd74-4214-bbd0-4a561d619411",
            "remark": "有人喜欢细的腰 有人喜欢长的腿 我不一样 我喜欢你喜欢我",
            "slideAdType": 0,
            "listAdType": false,
            "listAdTypeNew": 0,
            "width": null,
            "height": null,
            "videoTime": null,
            "visitCount": null,
            "showAdType": null,
            "privateAdImgUrl": null,
            "pay": false
        }, {
            "id": "e2e09588-2561-43ec-8e3c-bdb37b070bde",
            "title": null,
            "smallUrl": "http://lp-zhanghou-input.oss-cn-hangzhou.aliyuncs.com/source/e2e09588-2561-43ec-8e3c-bdb37b070bde_small.jpg",
            "visitUrl": "http://lp-zhanghou-input.oss-cn-hangzhou.aliyuncs.com/source/e2e09588-2561-43ec-8e3c-bdb37b070bde.jpg",
            "movUrl": "http://lp-zhanghou-input.oss-cn-hangzhou.aliyuncs.com/source/e2e09588-2561-43ec-8e3c-bdb37b070bde.mp4",
            "collectionFlag": false,
            "followFlag": false,
            "buyState": false,
            "tags": ["网红安琪"],
            "authorAvatar": "http://lp-zhanghou-input.oss-cn-hangzhou.aliyuncs.com/user/0d1ab597-053f-4db4-b8cd-a2155ae76a33/6cd3459f-76b5-44dc-a23c-b53266b8d727.JPG",
            "authorId": "0d1ab597-053f-4db4-b8cd-a2155ae76a33",
            "authorName": "小仙",
            "signature": null,
            "comType": 2,
            "statDataTypeKey": "c6f1b5a7-bd74-4214-bbd0-4a561d619411",
            "remark": "今天是三好学生 好饿好困好想你",
            "slideAdType": 0,
            "listAdType": false,
            "listAdTypeNew": 0,
            "width": null,
            "height": null,
            "videoTime": null,
            "visitCount": null,
            "showAdType": null,
            "privateAdImgUrl": null,
            "pay": false
        }, {
            "id": "01a9edd3-ff58-465f-84f9-5732a838b003",
            "title": null,
            "smallUrl": "http://lp-zhanghou-input.oss-cn-hangzhou.aliyuncs.com/source/01a9edd3-ff58-465f-84f9-5732a838b003_small.jpg",
            "visitUrl": "http://lp-zhanghou-input.oss-cn-hangzhou.aliyuncs.com/source/01a9edd3-ff58-465f-84f9-5732a838b003.jpg",
            "movUrl": "http://lp-zhanghou-input.oss-cn-hangzhou.aliyuncs.com/source/01a9edd3-ff58-465f-84f9-5732a838b003.mp4",
            "collectionFlag": false,
            "followFlag": false,
            "buyState": false,
            "tags": ["安琪baby"],
            "authorAvatar": "http://thirdwx.qlogo.cn/mmopen/vi_32/THXIN08WKl3qibxG3bdb5ElExMsAjddt87Pibd5yoLPPicVXvEjPOCfUbW1ZdISzydGmg4iaHCj3XJlibYXO3elg8cA/132",
            "authorId": "8851d5b0-bf8d-4490-8941-c868a467d71c",
            "authorName": "仙女没有猫",
            "signature": null,
            "comType": 2,
            "statDataTypeKey": "c6f1b5a7-bd74-4214-bbd0-4a561d619411",
            "remark": "听说女孩子讲话在后面加个“呐”就会很可爱 “我想给你吹唢呐” #拍散粉变装",
            "slideAdType": 0,
            "listAdType": false,
            "listAdTypeNew": 0,
            "width": null,
            "height": null,
            "videoTime": null,
            "visitCount": null,
            "showAdType": null,
            "privateAdImgUrl": null,
            "pay": false
        }, {
            "id": "8bc2e264-f96b-44ca-af85-bb01d5c784b9",
            "title": null,
            "smallUrl": "http://lp-zhanghou-input.oss-cn-hangzhou.aliyuncs.com/source/8bc2e264-f96b-44ca-af85-bb01d5c784b9_small.jpg",
            "visitUrl": "http://lp-zhanghou-input.oss-cn-hangzhou.aliyuncs.com/source/8bc2e264-f96b-44ca-af85-bb01d5c784b9.jpg",
            "movUrl": "http://lp-zhanghou-input.oss-cn-hangzhou.aliyuncs.com/source/8bc2e264-f96b-44ca-af85-bb01d5c784b9.mp4",
            "collectionFlag": false,
            "followFlag": false,
            "buyState": false,
            "tags": ["安琪baby"],
            "authorAvatar": "http://lp-zhanghou-input.oss-cn-hangzhou.aliyuncs.com/user/fdf8d2cf-3818-4198-86ed-1e9e24537fe9/2b02738d-a475-4c9a-bde2-0697d716e2c8.JPG",
            "authorId": "fdf8d2cf-3818-4198-86ed-1e9e24537fe9",
            "authorName": "樱木花道",
            "signature": null,
            "comType": 2,
            "statDataTypeKey": "c6f1b5a7-bd74-4214-bbd0-4a561d619411",
            "remark": "说一个你不想谈恋爱的理由吧！我替你保存#猛男舞蹈",
            "slideAdType": 0,
            "listAdType": false,
            "listAdTypeNew": 0,
            "width": null,
            "height": null,
            "videoTime": null,
            "visitCount": null,
            "showAdType": null,
            "privateAdImgUrl": null,
            "pay": false
        }, {
            "id": "16151ab5-0d9b-4a03-9b6b-9ad3b72587a2",
            "title": null,
            "smallUrl": "http://lp-zhanghou-input.oss-cn-hangzhou.aliyuncs.com/source/16151ab5-0d9b-4a03-9b6b-9ad3b72587a2_small.jpg",
            "visitUrl": "http://lp-zhanghou-input.oss-cn-hangzhou.aliyuncs.com/source/16151ab5-0d9b-4a03-9b6b-9ad3b72587a2.jpg",
            "movUrl": "http://lp-zhanghou-input.oss-cn-hangzhou.aliyuncs.com/source/16151ab5-0d9b-4a03-9b6b-9ad3b72587a2.mp4",
            "collectionFlag": false,
            "followFlag": false,
            "buyState": false,
            "tags": ["安琪baby"],
            "authorAvatar": "http://thirdqq.qlogo.cn/g?b=oidb&k=yCywWrp4DQz9R99aRdV6Iw&s=100&t=1574556949",
            "authorId": "e7efb41d-6034-467c-9945-6d983b747199",
            "authorName": "狐之恋",
            "signature": null,
            "comType": 2,
            "statDataTypeKey": "c6f1b5a7-bd74-4214-bbd0-4a561d619411",
            "remark": "你家真穷 我说想做你女朋友 你说没门 #飞吻变装",
            "slideAdType": 0,
            "listAdType": false,
            "listAdTypeNew": 0,
            "width": null,
            "height": null,
            "videoTime": null,
            "visitCount": null,
            "showAdType": null,
            "privateAdImgUrl": null,
            "pay": false
        }, {
            "id": "edda9da2-39be-411d-8684-7405148ab168",
            "title": null,
            "smallUrl": "http://lp-zhanghou-input.oss-cn-hangzhou.aliyuncs.com/source/edda9da2-39be-411d-8684-7405148ab168_small.jpg",
            "visitUrl": "http://lp-zhanghou-input.oss-cn-hangzhou.aliyuncs.com/source/edda9da2-39be-411d-8684-7405148ab168.jpg",
            "movUrl": "http://lp-zhanghou-input.oss-cn-hangzhou.aliyuncs.com/source/edda9da2-39be-411d-8684-7405148ab168.mp4",
            "collectionFlag": false,
            "followFlag": false,
            "buyState": false,
            "tags": ["安琪baby"],
            "authorAvatar": "http://lp-zhanghou-input.oss-cn-hangzhou.aliyuncs.com/user/58738498-5343-48b8-998f-8b45ef1ce7fc/e1f8eb8f-cec4-4abd-87ec-966b4680f162.JPG",
            "authorId": "58738498-5343-48b8-998f-8b45ef1ce7fc",
            "authorName": "我爱吉斯的",
            "signature": "高清动态壁纸，关注我点赞后，我可以教你怎么设置，要原图评论留言?",
            "comType": 2,
            "statDataTypeKey": "c6f1b5a7-bd74-4214-bbd0-4a561d619411",
            "remark": "我长这么好看完全归功于我的父母  他们给了我这张胡说八道的嘴",
            "slideAdType": 0,
            "listAdType": false,
            "listAdTypeNew": 0,
            "width": null,
            "height": null,
            "videoTime": null,
            "visitCount": null,
            "showAdType": null,
            "privateAdImgUrl": null,
            "pay": false
        }, {
            "id": "0916482e-efa7-4f1a-b12c-2928e5b1db85",
            "title": null,
            "smallUrl": "http://lp-zhanghou-input.oss-cn-hangzhou.aliyuncs.com/source/0916482e-efa7-4f1a-b12c-2928e5b1db85_small.jpg",
            "visitUrl": "http://lp-zhanghou-input.oss-cn-hangzhou.aliyuncs.com/source/0916482e-efa7-4f1a-b12c-2928e5b1db85.jpg",
            "movUrl": "http://lp-zhanghou-input.oss-cn-hangzhou.aliyuncs.com/source/0916482e-efa7-4f1a-b12c-2928e5b1db85.mp4",
            "collectionFlag": false,
            "followFlag": false,
            "buyState": false,
            "tags": ["安琪"],
            "authorAvatar": "http://thirdwx.qlogo.cn/mmopen/vi_32/fabAX5UEsdPiaar1OhibQVC9teunnhvEvMtJe6U7nzqoibsWhTiamTJAo0YeqjzMbKhR5sS4E7icHrwUJoOdgjGzHtA/132",
            "authorId": "944ad713-728c-4c33-b966-2d9922063ee9",
            "authorName": "迎风",
            "signature": null,
            "comType": 2,
            "statDataTypeKey": "c6f1b5a7-bd74-4214-bbd0-4a561d619411",
            "remark": "睡眠的拼音是shuimian  失眠的拼音是shimian 辗转反侧夜不能寐  原来是少了u",
            "slideAdType": 0,
            "listAdType": false,
            "listAdTypeNew": 0,
            "width": null,
            "height": null,
            "videoTime": null,
            "visitCount": null,
            "showAdType": null,
            "privateAdImgUrl": null,
            "pay": false
        }, {
            "id": "85b452c8-b736-45bf-9b85-0194dbcea682",
            "title": null,
            "smallUrl": "http://lp-zhanghou-input.oss-cn-hangzhou.aliyuncs.com/source/85b452c8-b736-45bf-9b85-0194dbcea682_small.jpg",
            "visitUrl": "http://lp-zhanghou-input.oss-cn-hangzhou.aliyuncs.com/source/85b452c8-b736-45bf-9b85-0194dbcea682.jpg",
            "movUrl": "http://lp-zhanghou-input.oss-cn-hangzhou.aliyuncs.com/source/85b452c8-b736-45bf-9b85-0194dbcea682.mp4",
            "collectionFlag": false,
            "followFlag": false,
            "buyState": false,
            "tags": ["网红安琪"],
            "authorAvatar": "http://lp-zhanghou-input.oss-cn-hangzhou.aliyuncs.com/user/75a2bd89-9e0e-4f8a-a3e8-b12521628a4e/db07d65e-de50-4f70-8e30-d14e4293ab33.JPG",
            "authorId": "75a2bd89-9e0e-4f8a-a3e8-b12521628a4e",
            "authorName": "第四代火影",
            "signature": "合作，定制加️：dtbz6666",
            "comType": 2,
            "statDataTypeKey": "c6f1b5a7-bd74-4214-bbd0-4a561d619411",
            "remark": "让你嘴角上扬的那个人是谁",
            "slideAdType": 0,
            "listAdType": false,
            "listAdTypeNew": 0,
            "width": null,
            "height": null,
            "videoTime": null,
            "visitCount": null,
            "showAdType": null,
            "privateAdImgUrl": null,
            "pay": false
        }]
    }
}
