{
    "code": 0,
    "msg": "",
    "url": null,
    "data": {
        "totalSize": 313,
        "totalPageCount": 10,
        "pageIndex": 6,
        "pageSize": 12,
        "list": [{
            "id": "1961f4a9-7f57-4cac-8a8a-fb9e0dd9d784",
            "title": null,
            "smallUrl": "http://lp-zhanghou-input.oss-cn-hangzhou.aliyuncs.com/source/1961f4a9-7f57-4cac-8a8a-fb9e0dd9d784_small.jpg",
            "visitUrl": "http://lp-zhanghou-input.oss-cn-hangzhou.aliyuncs.com/source/1961f4a9-7f57-4cac-8a8a-fb9e0dd9d784.jpg",
            "movUrl": "http://lp-zhanghou-input.oss-cn-hangzhou.aliyuncs.com/source/1961f4a9-7f57-4cac-8a8a-fb9e0dd9d784.mp4",
            "collectionFlag": false,
            "followFlag": false,
            "buyState": false,
            "tags": ["情侣壁纸", "唯美壁纸", "情侣壁纸女"],
            "authorAvatar": "http://lp-zhanghou-input.oss-cn-hangzhou.aliyuncs.com/user/030adead-4bfb-48e4-9ebf-3b8d9ae37999/c1be87ef-318a-49b0-97bf-3e1457596d75.JPG",
            "authorId": "030adead-4bfb-48e4-9ebf-3b8d9ae37999",
            "authorName": "养猪的仙女",
            "signature": null,
            "comType": 9,
            "statDataTypeKey": "110",
            "remark": "情侣壁纸#情侣壁纸 #送你送你一张动态壁纸",
            "slideAdType": 0,
            "listAdType": false,
            "listAdTypeNew": 0,
            "width": null,
            "height": null
        }, {
            "id": "614539e4-ba61-4ba5-9a6e-cc3baa8cb8ff",
            "title": null,
            "smallUrl": "http://lp-zhanghou-input.oss-cn-hangzhou.aliyuncs.com/source/614539e4-ba61-4ba5-9a6e-cc3baa8cb8ff_small.jpg",
            "visitUrl": "http://lp-zhanghou-input.oss-cn-hangzhou.aliyuncs.com/source/614539e4-ba61-4ba5-9a6e-cc3baa8cb8ff.jpg",
            "movUrl": "http://lp-zhanghou-input.oss-cn-hangzhou.aliyuncs.com/source/614539e4-ba61-4ba5-9a6e-cc3baa8cb8ff.mp4",
            "collectionFlag": false,
            "followFlag": false,
            "buyState": false,
            "tags": null,
            "authorAvatar": "http://lp-zhanghou-input.oss-cn-hangzhou.aliyuncs.com/user/dea353bb-6fe1-4f3a-b159-6b77bc669fd6/f2410911-dfb6-4a82-8e77-29d35e51fc52.JPG",
            "authorId": "dea353bb-6fe1-4f3a-b159-6b77bc669fd6",
            "authorName": "闫孝慈妈",
            "signature": null,
            "comType": 9,
            "statDataTypeKey": "110",
            "remark": "蓝色护眼壁纸女版",
            "slideAdType": 0,
            "listAdType": false,
            "listAdTypeNew": 0,
            "width": null,
            "height": null
        }, {
            "id": "1aedeba6-9462-4bd6-a14a-fb39b6cdb6da",
            "title": null,
            "smallUrl": "http://lp-zhanghou-input.oss-cn-hangzhou.aliyuncs.com/source/1aedeba6-9462-4bd6-a14a-fb39b6cdb6da_small.jpg",
            "visitUrl": "http://lp-zhanghou-input.oss-cn-hangzhou.aliyuncs.com/source/1aedeba6-9462-4bd6-a14a-fb39b6cdb6da.jpg",
            "movUrl": "http://lp-zhanghou-input.oss-cn-hangzhou.aliyuncs.com/source/1aedeba6-9462-4bd6-a14a-fb39b6cdb6da.mp4",
            "collectionFlag": false,
            "followFlag": false,
            "buyState": false,
            "tags": ["动态壁纸"],
            "authorAvatar": "http://lp-zhanghou-input.oss-cn-hangzhou.aliyuncs.com/user/d57fd561-ef67-4c6f-8911-02d157f9dedb/2e82439d-9c8f-4629-bc1a-018a7fdfa28c.JPG",
            "authorId": "d57fd561-ef67-4c6f-8911-02d157f9dedb",
            "authorName": "Secret?",
            "signature": null,
            "comType": 9,
            "statDataTypeKey": "110",
            "remark": "壁纸",
            "slideAdType": 0,
            "listAdType": false,
            "listAdTypeNew": 0,
            "width": null,
            "height": null
        }, {
            "id": "8335f6fa-fb44-4ac5-bdae-c61023fd5257",
            "title": null,
            "smallUrl": "http://lp-zhanghou-input.oss-cn-hangzhou.aliyuncs.com/source/8335f6fa-fb44-4ac5-bdae-c61023fd5257_small.jpg",
            "visitUrl": "http://lp-zhanghou-input.oss-cn-hangzhou.aliyuncs.com/source/8335f6fa-fb44-4ac5-bdae-c61023fd5257.jpg",
            "movUrl": "http://lp-zhanghou-input.oss-cn-hangzhou.aliyuncs.com/source/8335f6fa-fb44-4ac5-bdae-c61023fd5257.mp4",
            "collectionFlag": false,
            "followFlag": false,
            "buyState": false,
            "tags": ["动漫", "动漫", "情侣壁纸", "情侣壁纸", "高清手绘", "高清手绘", "明月下西樓制作", "明月下西樓制作"],
            "authorAvatar": "http://lp-zhanghou-input.oss-cn-hangzhou.aliyuncs.com/user/7ec9fb0a-ad09-4780-8ec0-293fcfa725d9/2132eceb-ed2e-4fba-9ad1-6be867f25d17.JPG",
            "authorId": "7ec9fb0a-ad09-4780-8ec0-293fcfa725d9",
            "authorName": "冰公主",
            "signature": null,
            "comType": 9,
            "statDataTypeKey": "110",
            "remark": "情侣壁纸，男〔原创〕",
            "slideAdType": 0,
            "listAdType": false,
            "listAdTypeNew": 0,
            "width": null,
            "height": null
        }, {
            "id": "e490ab49-0594-4a7b-a4af-8e499c0df77a",
            "title": null,
            "smallUrl": "http://lp-zhanghou-input.oss-cn-hangzhou.aliyuncs.com/source/e490ab49-0594-4a7b-a4af-8e499c0df77a_small.jpg",
            "visitUrl": "http://lp-zhanghou-input.oss-cn-hangzhou.aliyuncs.com/source/e490ab49-0594-4a7b-a4af-8e499c0df77a.jpg",
            "movUrl": "http://lp-zhanghou-input.oss-cn-hangzhou.aliyuncs.com/source/e490ab49-0594-4a7b-a4af-8e499c0df77a.mp4",
            "collectionFlag": false,
            "followFlag": false,
            "buyState": false,
            "tags": ["动漫", "动漫", "搬运", "wallpaper engine", "搬运", "wallpaper engine", "作者 Fala", "作者 Fala"],
            "authorAvatar": "http://lp-zhanghou-input.oss-cn-hangzhou.aliyuncs.com/user/eeb77668-9e7d-4b41-9fd6-fc039feda9b6/6822e32c-abd5-4cba-9d5f-189b29cfc212.JPG",
            "authorId": "eeb77668-9e7d-4b41-9fd6-fc039feda9b6",
            "authorName": "♡",
            "signature": null,
            "comType": 9,
            "statDataTypeKey": "110",
            "remark": "超壮观火龙喷火",
            "slideAdType": 0,
            "listAdType": false,
            "listAdTypeNew": 0,
            "width": null,
            "height": null
        }, {
            "id": "9e848693-f9e6-4569-a85c-96933d5bec3f",
            "title": null,
            "smallUrl": "http://lp-zhanghou-input.oss-cn-hangzhou.aliyuncs.com/source/9e848693-f9e6-4569-a85c-96933d5bec3f_small.jpg",
            "visitUrl": "http://lp-zhanghou-input.oss-cn-hangzhou.aliyuncs.com/source/9e848693-f9e6-4569-a85c-96933d5bec3f.jpg",
            "movUrl": "http://lp-zhanghou-input.oss-cn-hangzhou.aliyuncs.com/source/9e848693-f9e6-4569-a85c-96933d5bec3f.mp4",
            "collectionFlag": false,
            "followFlag": false,
            "buyState": false,
            "tags": ["动漫帅哥", "文字", "多幸运", "Love"],
            "authorAvatar": "http://lp-zhanghou-input.oss-cn-hangzhou.aliyuncs.com/user/14dfb7f8-3ecf-467e-8570-548cf24c78ae/2bff67f4-6eb4-4e77-9402-f598567c1e6e.JPG",
            "authorId": "14dfb7f8-3ecf-467e-8570-548cf24c78ae",
            "authorName": "人生（小号）",
            "signature": null,
            "comType": 9,
            "statDataTypeKey": "110",
            "remark": "做我的粉丝 我怎么能你们失望呢 盘他",
            "slideAdType": 0,
            "listAdType": false,
            "listAdTypeNew": 0,
            "width": null,
            "height": null
        }, {
            "id": "353c1390-82a2-424f-aa86-6eba43535f86",
            "title": null,
            "smallUrl": "http://lp-zhanghou-input.oss-cn-hangzhou.aliyuncs.com/source/353c1390-82a2-424f-aa86-6eba43535f86_small.jpg",
            "visitUrl": "http://lp-zhanghou-input.oss-cn-hangzhou.aliyuncs.com/source/353c1390-82a2-424f-aa86-6eba43535f86.jpg",
            "movUrl": "http://lp-zhanghou-input.oss-cn-hangzhou.aliyuncs.com/source/353c1390-82a2-424f-aa86-6eba43535f86.mp4",
            "collectionFlag": false,
            "followFlag": false,
            "buyState": false,
            "tags": ["情侣壁纸", "星空", "七夕节", "烟花特效"],
            "authorAvatar": "http://lp-zhanghou-input.oss-cn-hangzhou.aliyuncs.com/user/18aa4b0b-d22b-44ef-b190-90d093419c5b/1e6fdfb2-d21a-4842-a3ad-30cf43f27c3a.JPG",
            "authorId": "18aa4b0b-d22b-44ef-b190-90d093419c5b",
            "authorName": "WLAzvfif少年",
            "signature": null,
            "comType": 9,
            "statDataTypeKey": "110",
            "remark": "七夕情侣动态壁纸",
            "slideAdType": 0,
            "listAdType": false,
            "listAdTypeNew": 0,
            "width": null,
            "height": null
        }, {
            "id": "60a44ae5-2f13-42ba-b3bd-8fe5a1a56cb0",
            "title": null,
            "smallUrl": "http://lp-zhanghou-input.oss-cn-hangzhou.aliyuncs.com/source/60a44ae5-2f13-42ba-b3bd-8fe5a1a56cb0_small.jpg",
            "visitUrl": "http://lp-zhanghou-input.oss-cn-hangzhou.aliyuncs.com/source/60a44ae5-2f13-42ba-b3bd-8fe5a1a56cb0.jpg",
            "movUrl": "http://lp-zhanghou-input.oss-cn-hangzhou.aliyuncs.com/source/60a44ae5-2f13-42ba-b3bd-8fe5a1a56cb0.mp4",
            "collectionFlag": false,
            "followFlag": false,
            "buyState": false,
            "tags": ["视觉", "情侣壁纸", "星光特效", "无声壁纸"],
            "authorAvatar": "http://lp-zhanghou-input.oss-cn-hangzhou.aliyuncs.com/user/44abe930-3c6a-4169-911e-55c489f08de2/c9a41088-6fe5-4d69-a091-f4e1f998f719.JPG",
            "authorId": "44abe930-3c6a-4169-911e-55c489f08de2",
            "authorName": "乄男人似烟丶烟涩苦",
            "signature": null,
            "comType": 9,
            "statDataTypeKey": "110",
            "remark": "水晶爱情",
            "slideAdType": 0,
            "listAdType": false,
            "listAdTypeNew": 0,
            "width": null,
            "height": null
        }, {
            "id": "00171e49-2326-4f99-a8f1-48c1ceef09fe",
            "title": null,
            "smallUrl": "http://lp-zhanghou-input.oss-cn-hangzhou.aliyuncs.com/source/00171e49-2326-4f99-a8f1-48c1ceef09fe_small.jpg",
            "visitUrl": "http://lp-zhanghou-input.oss-cn-hangzhou.aliyuncs.com/source/00171e49-2326-4f99-a8f1-48c1ceef09fe.jpg",
            "movUrl": "http://lp-zhanghou-input.oss-cn-hangzhou.aliyuncs.com/source/00171e49-2326-4f99-a8f1-48c1ceef09fe.mp4",
            "collectionFlag": false,
            "followFlag": false,
            "buyState": false,
            "tags": ["星空", "情侣", "恋爱", "羽毛"],
            "authorAvatar": "http://lp-zhanghou-input.oss-cn-hangzhou.aliyuncs.com/user/4e123026-ce1f-417b-990f-390c5f738dae/107ff717-9044-415c-8b63-e1a1c8801c9d.JPG",
            "authorId": "4e123026-ce1f-417b-990f-390c5f738dae",
            "authorName": "ღ᭄ꦿ 像̶极̶了̶感̶情̶",
            "signature": null,
            "comType": 9,
            "statDataTypeKey": "110",
            "remark": "说出你喜欢的，我会加油做的^_^",
            "slideAdType": 0,
            "listAdType": false,
            "listAdTypeNew": 0,
            "width": null,
            "height": null
        }, {
            "id": "983765eb-949b-4021-ba52-ab490e4b7e6b",
            "title": null,
            "smallUrl": "http://lp-zhanghou-input.oss-cn-hangzhou.aliyuncs.com/source/983765eb-949b-4021-ba52-ab490e4b7e6b_small.jpg",
            "visitUrl": "http://lp-zhanghou-input.oss-cn-hangzhou.aliyuncs.com/source/983765eb-949b-4021-ba52-ab490e4b7e6b.jpg",
            "movUrl": "http://lp-zhanghou-input.oss-cn-hangzhou.aliyuncs.com/source/983765eb-949b-4021-ba52-ab490e4b7e6b.mp4",
            "collectionFlag": false,
            "followFlag": false,
            "buyState": false,
            "tags": ["蓝天白云", "极光", "流星雨"],
            "authorAvatar": "http://lp-zhanghou-input.oss-cn-hangzhou.aliyuncs.com/user/b707e3c4-3e70-44de-bf2f-44d265354453/a727cff4-3229-4cfe-957a-012b7046d058.JPG",
            "authorId": "b707e3c4-3e70-44de-bf2f-44d265354453",
            "authorName": "缘创♡",
            "signature": null,
            "comType": 9,
            "statDataTypeKey": "110",
            "remark": "LOVE云",
            "slideAdType": 0,
            "listAdType": false,
            "listAdTypeNew": 0,
            "width": null,
            "height": null
        }, {
            "id": "f06371f5-d7af-4618-bc2a-6c1f46c53ebe",
            "title": null,
            "smallUrl": "http://lp-zhanghou-input.oss-cn-hangzhou.aliyuncs.com/source/f06371f5-d7af-4618-bc2a-6c1f46c53ebe_small.jpg",
            "visitUrl": "http://lp-zhanghou-input.oss-cn-hangzhou.aliyuncs.com/source/f06371f5-d7af-4618-bc2a-6c1f46c53ebe.jpg",
            "movUrl": "http://lp-zhanghou-input.oss-cn-hangzhou.aliyuncs.com/source/f06371f5-d7af-4618-bc2a-6c1f46c53ebe.mp4",
            "collectionFlag": false,
            "followFlag": false,
            "buyState": false,
            "tags": ["视觉", "合集"],
            "authorAvatar": "http://lp-zhanghou-input.oss-cn-hangzhou.aliyuncs.com/user/8325e0da-c4ca-4a75-8cc6-ae2fa52286b8/89b4b391-3ef6-4201-b361-4bb4305f1d78.JPG",
            "authorId": "8325e0da-c4ca-4a75-8cc6-ae2fa52286b8",
            "authorName": "小猫咪",
            "signature": null,
            "comType": 9,
            "statDataTypeKey": "110",
            "remark": "横屏情侣壁纸",
            "slideAdType": 0,
            "listAdType": false,
            "listAdTypeNew": 0,
            "width": null,
            "height": null
        }, {
            "id": "0a185711-79e4-4af2-a5b8-edf60ce882bf",
            "title": null,
            "smallUrl": "http://lp-zhanghou-input.oss-cn-hangzhou.aliyuncs.com/source/0a185711-79e4-4af2-a5b8-edf60ce882bf_small.jpg",
            "visitUrl": "http://lp-zhanghou-input.oss-cn-hangzhou.aliyuncs.com/source/0a185711-79e4-4af2-a5b8-edf60ce882bf.jpg",
            "movUrl": "http://lp-zhanghou-input.oss-cn-hangzhou.aliyuncs.com/source/0a185711-79e4-4af2-a5b8-edf60ce882bf.mp4",
            "collectionFlag": false,
            "followFlag": false,
            "buyState": false,
            "tags": ["可爱卡通", "情侣壁纸男"],
            "authorAvatar": "http://lp-zhanghou-input.oss-cn-hangzhou.aliyuncs.com/user/0fc12094-aa56-4a26-a7a0-498475ee4752/254132ac-9725-4d8c-bb82-7cba75ac3ae1.JPG",
            "authorId": "0fc12094-aa56-4a26-a7a0-498475ee4752",
            "authorName": "夏沫凉、",
            "signature": null,
            "comType": 9,
            "statDataTypeKey": "110",
            "remark": "情侣壁纸女版",
            "slideAdType": 0,
            "listAdType": false,
            "listAdTypeNew": 0,
            "width": null,
            "height": null
        }]
    }
}
